fryhcs/__init__.py
fryhcs/__main__.py
fryhcs/admin.py
fryhcs/apps.py
fryhcs/cmdline.py
fryhcs/config.py
fryhcs/element.py
fryhcs/fileiter.py
fryhcs/models.py
fryhcs/page.py
fryhcs/reload.py
fryhcs/signals.py
fryhcs/spec.py
fryhcs/urls.py
fryhcs/utils.py
fryhcs/views.py
fryhcs/css/__init__.py
fryhcs/css/collector.py
fryhcs/css/color.py
fryhcs/css/generator.py
fryhcs/css/modifiers.py
fryhcs/css/plugin.py
fryhcs/css/preflight.css
fryhcs/css/style.py
fryhcs/css/utilities.py
fryhcs/fry/__init__.py
fryhcs/fry/fry.ppeg
fryhcs/fry/frylexer.py
fryhcs/fry/fryloader.py
fryhcs/fry/generator.py
fryhcs/fry/grammar.py
fryhcs/js/__init__.py
fryhcs/js/generator.py
fryhcs/management/__init__.py
fryhcs/management/commands/__init__.py
fryhcs/management/commands/fryhcs.py
fryhcs/migrations/__init__.py
fryhcs/static/js/fryhcs.js
fryhcs-0.2.43.dist-info/METADATA
fryhcs-0.2.43.dist-info/WHEEL
fryhcs-0.2.43.dist-info/entry_points.txt
fryhcs-0.2.43.dist-info/licenses/LICENSE
fryhcs-0.2.43.dist-info/RECORD
