Metadata-Version: 2.3
Name: fryhcs
Version: 0.2.43
Summary: A python library to generate HTML, Javascript and CSS, based on fry file
Project-URL: Homepage, https://github.com/frybox/fryhcs
Project-URL: Bug Tracker, https://github.com/frybox/fryhcs/issues
Project-URL: Source, https://github.com/frybox/fryhcs
Author-email: Zenk Ju <juzejian@gmail.com>
License: MIT
Keywords: django,flask,fry,fryhcs
Classifier: License :: OSI Approved :: MIT License
Classifier: Operating System :: OS Independent
Classifier: Programming Language :: Python :: 3
Requires-Python: >=3.8
Requires-Dist: coloraide
Requires-Dist: flask
Requires-Dist: parsimonious
